LICENSE
README.rst
scimschema/VERSION
scimschema/__init__.py
scimschema/_model/__init__.py
scimschema/_model/attribute.py
scimschema/_model/model.py
scimschema/_model/schema_response.py
scimschema/_model/scim_exceptions.py
scimschema/core_schemas/SCIM Core2 enterpriseuser spec.json
scimschema/core_schemas/SCIM Core2 error spec.json
scimschema/core_schemas/SCIM Core2 group spec.json
scimschema/core_schemas/SCIM Core2 resourcetype spec.json
scimschema/core_schemas/SCIM Core2 schema spec.json
scimschema/core_schemas/SCIM Core2 serviceproviderconfig spec.json
scimschema/core_schemas/SCIM Core2 user spec.json
scimschema/core_schemas/__init__.py
scimschema/py.typed
scimschema-0.3.1.dist-info/LICENSE
scimschema-0.3.1.dist-info/WHEEL
scimschema-0.3.1.dist-info/METADATA
scimschema-0.3.1.dist-info/RECORD
